shopcloud_microservice/__init__.py
shopcloud_microservice/__main__.py
shopcloud_microservice/_version.py
shopcloud_microservice/app.py
shopcloud_microservice/audit.py
shopcloud_microservice/backup.py
shopcloud_microservice/cli.py
shopcloud_microservice/configs.py
shopcloud_microservice/exceptions.py
shopcloud_microservice/helpers.py
shopcloud_microservice/security.py
shopcloud_microservice/steps.py
shopcloud_microservice-0.37.0.dist-info/licenses/LICENSE
shopcloud_microservice-0.37.0.dist-info/METADATA
shopcloud_microservice-0.37.0.dist-info/WHEEL
shopcloud_microservice-0.37.0.dist-info/entry_points.txt
shopcloud_microservice-0.37.0.dist-info/top_level.txt
shopcloud_microservice-0.37.0.dist-info/RECORD
