Metadata-Version: 2.4
Name: shopcloud-microservice
Version: 0.37.0
Summary: CLI tool for manage microservices
Author-email: Konstantin Stoldt <konstantin.stoldt@talk-point.de>
License: MIT
Project-URL: Homepage, https://github.com/Talk-Point/shopcloud-microservice-cli
Project-URL: Repository, https://github.com/Talk-Point/shopcloud-microservice-cli
Keywords: CLI
Classifier: Development Status :: 4 - Beta
Classifier: Intended Audience :: Developers
Classifier: Programming Language :: Python :: 3
Classifier: Programming Language :: Python :: 3.8
Classifier: Programming Language :: Python :: 3.9
Classifier: Programming Language :: Python :: 3.10
Classifier: Programming Language :: Python :: 3.11
Classifier: Programming Language :: Python :: 3.12
Requires-Python: >=3.8
License-File: LICENSE
Requires-Dist: pyyaml
Requires-Dist: requests
Requires-Dist: joblib
Requires-Dist: shopcloud_secrethub
Dynamic: license-file
